pycontrolaudacity_cli/__init__.py
pycontrolaudacity_cli/cli.py
pycontrolaudacity_cli-0.1.5.dist-info/LICENSE
pycontrolaudacity_cli-0.1.5.dist-info/METADATA
pycontrolaudacity_cli-0.1.5.dist-info/WHEEL
pycontrolaudacity_cli-0.1.5.dist-info/entry_points.txt
pycontrolaudacity_cli-0.1.5.dist-info/RECORD
