Metadata-Version: 2.1
Name: pycontrolaudacity-cli
Version: 0.1.5
Summary: Cria rótulos e atualiza o timestamp de uma trilha de áudio no Audacity, possibilitando seu posterior particionamento em fragmentos.
License: GPLv3 License
Author: dUnIO
Author-email: dunio.dev@gmail.com
Maintainer: dUnIO
Maintainer-email: dunio.dev@gmail.com
Requires-Python: >=3.11,<4.0
Classifier: Development Status :: 5 - Production/Stable
Classifier: Environment :: Console
Classifier: License :: Other/Proprietary License
Classifier: Natural Language :: Portuguese (Brazilian)
Classifier: Programming Language :: Python :: 3
Classifier: Programming Language :: Python :: 3.11
Classifier: Programming Language :: Python :: 3.12
Classifier: Topic :: Multimedia :: Sound/Audio
Project-URL: Bug Tracker, https://salsa.debian.org/dunio.dev/pycontrolaudacity-cli/isuues
Project-URL: Código, https://salsa.debian.org/dunio.dev/pycontrolaudacity-cli
Project-URL: Documentação, https://pycontrolaudacity-cli.readthedocs.io/pt-br/latest/
